bi_est_python/Mixture.py
bi_est_python/mixtureUtils.py
bi_est_python/pnu_em.py
bi_est_python-0.1.0.dist-info/LICENSE
bi_est_python-0.1.0.dist-info/METADATA
bi_est_python-0.1.0.dist-info/WHEEL
bi_est_python-0.1.0.dist-info/RECORD
