Metadata-Version: 2.1
Name: bi_est_python
Version: 0.1.0
Summary: [fork of claradepaolis/bi-est-python] Estimate bias in semisupervised data via nested Expectation Maximization
License: MIT
Author: Daniel Zeiberg
Author-email: zeiberg.d@northeastern.edu
Requires-Python: >=3.10,<4.0
Classifier: License :: OSI Approved :: MIT License
Classifier: Programming Language :: Python :: 3
Classifier: Programming Language :: Python :: 3.10
Classifier: Programming Language :: Python :: 3.11
Classifier: Programming Language :: Python :: 3.12
Requires-Dist: ipykernel (>=6.29.0,<7.0.0)
Requires-Dist: numpy (>=1.26.3,<2.0.0)
Requires-Dist: scikit-learn (>=1.4.0,<2.0.0)
Requires-Dist: scipy (>=1.12.0,<2.0.0)
